tests/__init__.py
tests/test_ActivelyLearnedModel.py
tests/test_AuxiliaryIntervalPredictor.py
tests/test_EnsembleHeteroscedasticRegression.py
tests/test_HeteroscedasticRegression.py
tests/test_HomoscedasticGPRegression.py
tests/test_Hshoe.py
tests/test_IJ.py
tests/test_MetamodelClassification.py
tests/test_MetamodelRegression.py
tests/test_QuantileRegression.py
tests/test_ShortTextClassification.py
tests/test_StructuredDataClassification.py
tests/test_classification_metrics.py
tests/test_regression_metrics.py
tests/test_utils.py
uq360/__init__.py
uq360/base.py
uq360/algorithms/__init__.py
uq360/algorithms/builtinuq.py
uq360/algorithms/posthocuq.py
uq360/algorithms/actively_learned_model/__init__.py
uq360/algorithms/actively_learned_model/actively_learned_model.py
uq360/algorithms/auxiliary_interval_predictor/__init__.py
uq360/algorithms/auxiliary_interval_predictor/auxiliary_interval_predictor.py
uq360/algorithms/blackbox_metamodel/__init__.py
uq360/algorithms/blackbox_metamodel/confidence_classification.py
uq360/algorithms/blackbox_metamodel/metamodel_classification.py
uq360/algorithms/blackbox_metamodel/metamodel_regression.py
uq360/algorithms/blackbox_metamodel/passthrough_classification.py
uq360/algorithms/blackbox_metamodel/short_text_classification.py
uq360/algorithms/blackbox_metamodel/structured_data_classification.py
uq360/algorithms/blackbox_metamodel/predictors/__init__.py
uq360/algorithms/blackbox_metamodel/predictors/predictor_driver.py
uq360/algorithms/blackbox_metamodel/predictors/base/__init__.py
uq360/algorithms/blackbox_metamodel/predictors/base/predictor_base.py
uq360/algorithms/blackbox_metamodel/predictors/core/__init__.py
uq360/algorithms/blackbox_metamodel/predictors/core/confidence.py
uq360/algorithms/blackbox_metamodel/predictors/core/passthrough.py
uq360/algorithms/blackbox_metamodel/predictors/core/short_text.py
uq360/algorithms/blackbox_metamodel/predictors/core/structured_data.py
uq360/algorithms/classification_calibration/__init__.py
uq360-0.2.dist-info/LICENSE
uq360-0.2.dist-info/METADATA
uq360-0.2.dist-info/WHEEL
uq360-0.2.dist-info/top_level.txt
uq360-0.2.dist-info/RECORD
