Metadata-Version: 2.1
Name: uq360
Version: 0.2
Summary: Uncertainty Quantification 360
Home-page: https://github.com/IBM/UQ360
Author: uq360 developers
Author-email: uq360@us.ibm.com
License: Apache License 2.0
Platform: UNKNOWN
License-File: LICENSE
Requires-Dist: numpy (<1.21,>=1.16.5)
Requires-Dist: scipy (>=1.2.0)
Requires-Dist: pandas (>=0.24.0)
Requires-Dist: scikit-learn (<1.0,>=0.22)
Requires-Dist: matplotlib (>=3.2)
Requires-Dist: autograd (>=1.3)
Requires-Dist: torch (>=1.6.0)
Requires-Dist: gpytorch (>=1.3.0)
Requires-Dist: botorch (>=0.3.2)
Requires-Dist: tqdm (==4.42.0)
Requires-Dist: tensorflow
Requires-Dist: tensorflow-hub
Requires-Dist: gitpython (==2.1.15)
Requires-Dist: umap-learn (==0.3.10)
Requires-Dist: tabulate
Requires-Dist: requests
